move_and_zip_task/__init__.py
move_and_zip_task/mover.py
move_and_zip_task-0.0.1.dist-info/METADATA
move_and_zip_task-0.0.1.dist-info/WHEEL
move_and_zip_task-0.0.1.dist-info/top_level.txt
move_and_zip_task-0.0.1.dist-info/RECORD
