Metadata-Version: 2.1
Name: move-and-zip-task
Version: 0.0.1
Summary: task_1 from gnanendra
Home-page: UNKNOWN
Author: Subhajit
Author-email: singha111subhajit@gmail.com
License: UNKNOWN
Keywords: python
Platform: UNKNOWN
Classifier: Development Status :: 1 - Planning
Classifier: Intended Audience :: Developers
Classifier: Programming Language :: Python :: 3
Classifier: Operating System :: Unix
Classifier: Operating System :: MacOS :: MacOS X
Classifier: Operating System :: Microsoft :: Windows
